csle_rest_api/__init__.py
csle_rest_api/__version__.py
csle_rest_api/rest_api.py
csle_rest_api/constants/__init__.py
csle_rest_api/constants/constants.py
csle_rest_api/pages/__init__.py
csle_rest_api/pages/about/__init__.py
csle_rest_api/pages/about/routes.py
csle_rest_api/pages/container_terminal/__init__.py
csle_rest_api/pages/container_terminal/routes.py
csle_rest_api/pages/control_plane/__init__.py
csle_rest_api/pages/control_plane/routes.py
csle_rest_api/pages/create_emulation/__init__.py
csle_rest_api/pages/create_emulation/routes.py
csle_rest_api/pages/downloads/__init__.py
csle_rest_api/pages/downloads/routes.py
csle_rest_api/pages/emulation_statistics/__init__.py
csle_rest_api/pages/emulation_statistics/routes.py
csle_rest_api/pages/emulations/__init__.py
csle_rest_api/pages/emulations/routes.py
csle_rest_api/pages/images/__init__.py
csle_rest_api/pages/images/routes.py
csle_rest_api/pages/jobs/__init__.py
csle_rest_api/pages/jobs/routes.py
csle_rest_api/pages/login/__init__.py
csle_rest_api/pages/login/routes.py
csle_rest_api/pages/logs_admin/__init__.py
csle_rest_api/pages/logs_admin/routes.py
csle_rest_api/pages/monitoring/__init__.py
csle_rest_api/pages/monitoring/routes.py
csle_rest_api/pages/policies/__init__.py
csle_rest_api/pages/policies/routes.py
csle_rest_api/pages/policy_examination/__init__.py
csle_rest_api/pages/policy_examination/routes.py
csle_rest_api/pages/recovery_ai/__init__.py
csle_rest_api/pages/recovery_ai/routes.py
csle_rest_api/pages/register/__init__.py
csle_rest_api/pages/register/routes.py
csle_rest_api/pages/sdn_controllers/__init__.py
csle_rest_api/pages/sdn_controllers/routes.py
csle_rest_api/pages/server_cluster/__init__.py
csle_rest_api/pages/server_cluster/routes.py
csle_rest_api/pages/simulations/__init__.py
csle_rest_api/pages/simulations/routes.py
csle_rest_api/pages/system_admin/__init__.py
csle_rest_api/pages/system_admin/routes.py
csle_rest_api/pages/system_models/__init__.py
csle_rest_api-0.9.45.dist-info/METADATA
csle_rest_api-0.9.45.dist-info/WHEEL
csle_rest_api-0.9.45.dist-info/top_level.txt
csle_rest_api-0.9.45.dist-info/RECORD
